media_recognition_proto/__init__.py
media_recognition_proto/client_pb2.py
media_recognition_proto/client_pb2.pyi
media_recognition_proto/client_pb2_grpc.py
media_recognition_proto/py.typed
media_recognition_proto-1.0.0.dist-info/METADATA
media_recognition_proto-1.0.0.dist-info/WHEEL
media_recognition_proto-1.0.0.dist-info/top_level.txt
media_recognition_proto-1.0.0.dist-info/RECORD
