Metadata-Version: 2.1
Name: media-recognition-proto
Version: 1.0.0
Summary: GRPC client for media_recognition_proto
Author: ci
Author-email: p.a.anokhin@gmail.com
